{
  "pools": [
    {
      "rolls": {
        "min": 1,
        "max": 6
      },
      "entries": [
        {
          "type": "minecraft:item",
          "weight": 3,
          "name": "minecraft:sponge",
          "functions": [
            {
              "function": "minecraft:set_count",
              "count": {
                "min": 3,
                "max": 6
              }
            }
          ]
        },
        {
          "type": "minecraft:item",
          "weight": 2,
          "name": "minecraft:potion",
          "functions": [
            {
              "function": "minecraft:set_potion",
              "id": "minecraft:long_turtle_master"
            }
          ],
          "conditions": [
            {
              "condition": "minecraft:random_chance",
              "chance": 0.33
            }
          ]
        },
        {
          "type": "minecraft:item",
          "weight": 3,
          "name": "minecraft:guardian_spawn_egg",
          "functions": [
            {
              "function": "minecraft:set_components",
              "components": {
                "minecraft:custom_name": {
                  "text": "Guardian Spawn Egg",
                  "color": "gold",
                  "italic": false
                },
                "minecraft:lore": [
                  {
                    "text": "Hint: use this on a spawner.",
                    "color": "gray",
                    "italic": false
                  }
                ],
                "minecraft:tooltip_display": {
                  "hidden_components": [
                    "minecraft:dyed_color"
                  ]
                }
              }
            }
          ],
          "conditions": [
            {
              "condition": "minecraft:random_chance",
              "chance": 0.05
            }
          ]
        },
        {
          "type": "minecraft:item",
          "name": "minecraft:trident",
          "functions": [
            {
              "function": "minecraft:set_enchantments",
              "enchantments": {
                "minecraft:riptide": {
                  "min": 1,
                  "max": 4
                }
              },
              "conditions": [
                {
                  "condition": "minecraft:random_chance",
                  "chance": 0.5
                }
              ]
            },
            {
              "function": "minecraft:set_enchantments",
              "enchantments": {
                "minecraft:mending": 1
              },
              "conditions": [
                {
                  "condition": "minecraft:random_chance",
                  "chance": 0.25
                }
              ]
            },
            {
              "function": "minecraft:set_enchantments",
              "enchantments": {
                "minecraft:impaling": {
                  "min": 0,
                  "max": 6
                },
                "minecraft:sharpness": {
                  "min": 0,
                  "max": 3
                },
                "minecraft:unbreaking": {
                  "min": 0,
                  "max": 6
                }
              }
            }
          ]
        },
        {
          "type": "minecraft:item",
          "name": "minecraft:trident",
          "functions": [
            {
              "function": "minecraft:set_enchantments",
              "enchantments": {
                "minecraft:loyalty": {
                  "min": 0,
                  "max": 5
                }
              },
              "conditions": [
                {
                  "condition": "minecraft:random_chance",
                  "chance": 0.5
                }
              ]
            },
            {
              "function": "minecraft:set_enchantments",
              "enchantments": {
                "minecraft:mending": 1
              },
              "conditions": [
                {
                  "condition": "minecraft:random_chance",
                  "chance": 0.25
                }
              ]
            },
            {
              "function": "minecraft:set_enchantments",
              "enchantments": {
                "minecraft:impaling": {
                  "min": 0,
                  "max": 6
                },
                "minecraft:channeling": {
                  "min": 0,
                  "max": 1
                },
                "minecraft:unbreaking": {
                  "min": 0,
                  "max": 6
                }
              }
            }
          ]
        },
        {
          "type": "minecraft:item",
          "name": "minecraft:fishing_rod",
          "functions": [
            {
              "function": "minecraft:set_enchantments",
              "enchantments": {
                "minecraft:luck_of_the_sea": {
                  "min": 1,
                  "max": 8
                }
              },
              "conditions": [
                {
                  "condition": "minecraft:random_chance",
                  "chance": 0.75
                }
              ]
            },
            {
              "function": "minecraft:set_enchantments",
              "enchantments": {
                "minecraft:mending": 1
              },
              "conditions": [
                {
                  "condition": "minecraft:random_chance",
                  "chance": 0.25
                }
              ]
            },
            {
              "function": "minecraft:set_enchantments",
              "enchantments": {
                "minecraft:lure": {
                  "min": 0,
                  "max": 5
                },
                "minecraft:knockback": {
                  "min": 0,
                  "max": 3
                },
                "minecraft:unbreaking": {
                  "min": 0,
                  "max": 6
                }
              }
            }
          ]
        },
        {
          "type": "minecraft:item",
          "weight": 3,
          "name": "minecraft:tnt",
          "functions": [
            {
              "function": "minecraft:set_count",
              "count": {
                "min": 4,
                "max": 8
              },
              "add": false
            }
          ]
        },
        {
          "type": "minecraft:item",
          "name": "minecraft:enchanted_golden_apple",
          "functions": [
            {
              "function": "minecraft:set_count",
              "count": {
                "type": "minecraft:constant",
                "value": 1
              }
            }
          ]
        },
        {
          "type": "minecraft:item",
          "weight": 2,
          "name": "minecraft:golden_apple",
          "functions": [
            {
              "function": "minecraft:set_count",
              "count": {
                "type": "minecraft:constant",
                "value": 5
              }
            }
          ]
        },
        {
          "type": "minecraft:item",
          "weight": 3,
          "name": "minecraft:cooked_salmon",
          "functions": [
            {
              "function": "minecraft:set_count",
              "count": {
                "type": "minecraft:constant",
                "value": 5
              },
              "add": true
            }
          ]
        },
        {
          "type": "minecraft:item",
          "weight": 3,
          "name": "minecraft:cooked_cod",
          "functions": [
            {
              "function": "minecraft:set_count",
              "count": {
                "type": "minecraft:constant",
                "value": 5
              },
              "add": true
            }
          ]
        },
        {
          "type": "minecraft:item",
          "weight": 3,
          "name": "minecraft:shulker_shell",
          "functions": [
            {
              "function": "minecraft:set_count",
              "count": {
                "min": 2,
                "max": 4
              },
              "add": false
            }
          ]
        },
        {
          "type": "minecraft:item",
          "weight": 2,
          "name": "minecraft:nautilus_shell",
          "functions": [
            {
              "function": "minecraft:set_count",
              "count": {
                "min": 1,
                "max": 2
              },
              "add": false
            }
          ]
        }
      ]
    }
  ]
}